tilings/__init__.py
tilings/assumptions.py
tilings/bijections.py
tilings/cli.py
tilings/exception.py
tilings/griddedperm.py
tilings/gui_launcher.py
tilings/misc.py
tilings/obstruction.py
tilings/py.typed
tilings/requirement.py
tilings/strategy_pack.py
tilings/tilescope.py
tilings/tiling.py
tilings/algorithms/__init__.py
tilings/algorithms/better_bounds.py
tilings/algorithms/enumeration.py
tilings/algorithms/factor.py
tilings/algorithms/fusion.py
tilings/algorithms/gridded_perm_generation.py
tilings/algorithms/gridded_perm_reduction.py
tilings/algorithms/guess_obstructions.py
tilings/algorithms/locally_factorable_shift.py
tilings/algorithms/map.py
tilings/algorithms/minimal_gridded_perms.py
tilings/algorithms/obstruction_inferral.py
tilings/algorithms/obstruction_transitivity.py
tilings/algorithms/requirement_placement.py
tilings/algorithms/row_col_separation.py
tilings/algorithms/sliding.py
tilings/algorithms/subclass_verification.py
tilings/strategies/__init__.py
tilings/strategies/abstract.py
tilings/strategies/assumption_insertion.py
tilings/strategies/assumption_splitting.py
tilings/strategies/cell_reduction.py
tilings/strategies/deflation.py
tilings/strategies/detect_components.py
tilings/strategies/dummy_constructor.py
tilings/strategies/dummy_strategy.py
tilings/strategies/experimental_verification.py
tilings/strategies/factor.py
tilings/strategies/monotone_sliding.py
tilings/strategies/obstruction_inferral.py
tilings/strategies/point_jumping.py
tilings/strategies/pointing.py
tilings/strategies/rearrange_assumption.py
tilings/strategies/relax_assumption.py
tilings/strategies/requirement_insertion.py
tilings/strategies/requirement_placement.py
tilings/strategies/row_and_col_separation.py
tilings/strategies/sliding.py
tilings/strategies/symmetry.py
tilings/strategies/unfusion.py
tilings/strategies/verification.py
tilings/strategies/fusion/__init__.py
tilings/strategies/fusion/component.py
tilings/strategies/fusion/constructor.py
tilings-4.1.0.dist-info/METADATA
tilings-4.1.0.dist-info/WHEEL
tilings-4.1.0.dist-info/entry_points.txt
tilings-4.1.0.dist-info/licenses/LICENSE
tilings-4.1.0.dist-info/RECORD
