Metadata-Version: 2.4
Name: tilings
Version: 4.1.0
Summary: A Python library for gridded permutations and tilings.
Project-URL: Source, https://github.com/PermutaTriangle/Tilings
Project-URL: Tracker, https://github.com/PermutaTriangle/Tilings/issues
Author-email: Permuta Triangle <permutatriangle@gmail.com>
License: BSD-3-Clause
License-File: LICENSE
Keywords: avoid,class,contain,grid,gridded,occurrences,pattern,perm,permutation,tiling
Classifier: Development Status :: 5 - Production/Stable
Classifier: Intended Audience :: Education
Classifier: Intended Audience :: Science/Research
Classifier: License :: OSI Approved :: BSD License
Classifier: Programming Language :: Python :: 3
Classifier: Programming Language :: Python :: 3.10
Classifier: Programming Language :: Python :: 3.11
Classifier: Programming Language :: Python :: 3.12
Classifier: Programming Language :: Python :: 3.13
Classifier: Programming Language :: Python :: Implementation :: CPython
Classifier: Programming Language :: Python :: Implementation :: PyPy
Classifier: Topic :: Education
Classifier: Topic :: Scientific/Engineering :: Mathematics
Requires-Python: >=3.10
Requires-Dist: comb-spec-searcher>=4.2.1
Requires-Dist: permuta>=2.3.0
